stomper/__init__.py
stomper/stomp_10.py
stomper/stomp_11.py
stomper/stompbuffer.py
stomper/utils.py
stomper/examples/__init__.py
stomper/examples/receiver.py
stomper/examples/sender.py
stomper/examples/stompbuffer-rx.py
stomper/examples/stompbuffer-tx.py
stomper/examples/stomper_usage.py
stomper/tests/__init__.py
stomper/tests/teststompbuffer.py
stomper/tests/teststomper_10.py
stomper/tests/teststomper_11.py
stomper-0.4.3.dist-info/LICENSE
stomper-0.4.3.dist-info/METADATA
stomper-0.4.3.dist-info/WHEEL
stomper-0.4.3.dist-info/top_level.txt
stomper-0.4.3.dist-info/RECORD
