Metadata-Version: 2.1
Name: stomper
Version: 0.4.3
Summary: This is a transport neutral client implementation of the STOMP protocol.
Home-page: https://github.com/oisinmulvihill/stomper
Author: Oisin Mulvihill
Author-email: oisin.mulvihilli@gmail.com
License: http://www.apache.org/licenses/LICENSE-2.0
Platform: UNKNOWN
Classifier: Development Status :: 4 - Beta
Classifier: Intended Audience :: Developers
Classifier: License :: OSI Approved :: Apache Software License
Classifier: Programming Language :: Python
Requires-Dist: future
